sutton_signwriting_core/__init__.py
sutton_signwriting_core/convert.py
sutton_signwriting_core/datatypes.py
sutton_signwriting_core/fsw.py
sutton_signwriting_core/fswquery.py
sutton_signwriting_core/py.typed
sutton_signwriting_core/regex.py
sutton_signwriting_core/style.py
sutton_signwriting_core/swu.py
sutton_signwriting_core/swuquery.py
sutton_signwriting_core/symid_arr.py
sutton_signwriting_core-1.1.3.dist-info/METADATA
sutton_signwriting_core-1.1.3.dist-info/WHEEL
sutton_signwriting_core-1.1.3.dist-info/licenses/LICENSE
sutton_signwriting_core-1.1.3.dist-info/RECORD
