Metadata-Version: 2.4
Name: sutton-signwriting-core
Version: 1.1.3
Summary: Python tools for Sutton SignWriting core functionality.
License: MIT
License-File: LICENSE
Keywords: signwriting,fsw,swu,sign-language,sutton-signwriting
Author: Steve Slevinski
Author-email: Slevinski@signwriting.org
Requires-Python: >=3.11,<4.0
Classifier: Intended Audience :: Developers
Classifier: License :: OSI Approved :: MIT License
Classifier: Programming Language :: Python :: 3
Classifier: Programming Language :: Python :: 3.11
Classifier: Programming Language :: Python :: 3.12
Classifier: Programming Language :: Python :: 3.13
Classifier: Programming Language :: Python :: 3.14
Classifier: Topic :: Scientific/Engineering :: Information Analysis
Classifier: Topic :: Text Processing :: Linguistic
Classifier: Typing :: Typed
Requires-Dist: roman-numerals (==4.0.0)
Project-URL: Documentation, https://sutton-signwriting.io/core-py
Project-URL: Homepage, https://github.com/sutton-signwriting/core-py
Project-URL: Repository, https://github.com/sutton-signwriting/core-py
